github_watcher/__init__.py
github_watcher/settings.py
github_watcher/util.py
github_watcher/commands/__init__.py
github_watcher/commands/check.py
github_watcher/commands/config.py
github_watcher/commands/run.py
github_watcher/services/__init__.py
github_watcher/services/git.py
github_watcher-4.1.data/scripts/github-watcher
tests/__init__.py
tests/test_check.py
tests/test_config.py
tests/test_git.py
tests/test_run.py
tests/test_util.py
github_watcher-4.1.dist-info/METADATA
github_watcher-4.1.dist-info/WHEEL
github_watcher-4.1.dist-info/top_level.txt
github_watcher-4.1.dist-info/RECORD
