Metadata-Version: 2.1
Name: github-watcher
Version: 4.1
Summary: Monitors files/directories on github and alerts you when someone submits a PR with changes
Home-page: https://github.com/akellehe/github-watcher
Author: Andrew Kelleher
Author-email: keats.kelleher@gmail.com
License: UNKNOWN
Platform: UNKNOWN
Requires-Dist: unidiff (==0.5.4)
Requires-Dist: requests (==2.20.0)
Requires-Dist: PyYAML (==3.13)
Requires-Dist: PyGithub (==1.43)
Requires-Dist: pync (==2.0.3)
